XStatic_Bootstrap_SCSS-3.3.7.1-py2.7-nspkg.pth
XStatic_Bootstrap_SCSS-3.3.7.1.dist-info/DESCRIPTION.rst
XStatic_Bootstrap_SCSS-3.3.7.1.dist-info/METADATA
XStatic_Bootstrap_SCSS-3.3.7.1.dist-info/RECORD
XStatic_Bootstrap_SCSS-3.3.7.1.dist-info/WHEEL
XStatic_Bootstrap_SCSS-3.3.7.1.dist-info/metadata.json
XStatic_Bootstrap_SCSS-3.3.7.1.dist-info/namespace_packages.txt
XStatic_Bootstrap_SCSS-3.3.7.1.dist-info/top_level.txt
xstatic/pkg/bootstrap_scss/__init__.py
xstatic/pkg/bootstrap_scss/data/fonts/bootstrap/glyphicons-halflings-regular.eot
xstatic/pkg/bootstrap_scss/data/fonts/bootstrap/glyphicons-halflings-regular.svg
xstatic/pkg/bootstrap_scss/data/fonts/bootstrap/glyphicons-halflings-regular.ttf
xstatic/pkg/bootstrap_scss/data/fonts/bootstrap/glyphicons-halflings-regular.woff
xstatic/pkg/bootstrap_scss/data/fonts/bootstrap/glyphicons-halflings-regular.woff2
xstatic/pkg/bootstrap_scss/data/js/bootstrap-sprockets.js
xstatic/pkg/bootstrap_scss/data/js/bootstrap.js
xstatic/pkg/bootstrap_scss/data/js/bootstrap.min.js
xstatic/pkg/bootstrap_scss/data/js/bootstrap/affix.js
xstatic/pkg/bootstrap_scss/data/js/bootstrap/alert.js
xstatic/pkg/bootstrap_scss/data/js/bootstrap/button.js
xstatic/pkg/bootstrap_scss/data/js/bootstrap/carousel.js
xstatic/pkg/bootstrap_scss/data/js/bootstrap/collapse.js
xstatic/pkg/bootstrap_scss/data/js/bootstrap/dropdown.js
xstatic/pkg/bootstrap_scss/data/js/bootstrap/modal.js
xstatic/pkg/bootstrap_scss/data/js/bootstrap/popover.js
xstatic/pkg/bootstrap_scss/data/js/bootstrap/scrollspy.js
xstatic/pkg/bootstrap_scss/data/js/bootstrap/tab.js
xstatic/pkg/bootstrap_scss/data/js/bootstrap/tooltip.js
xstatic/pkg/bootstrap_scss/data/js/bootstrap/transition.js
xstatic/pkg/bootstrap_scss/data/scss/_bootstrap-compass.scss
xstatic/pkg/bootstrap_scss/data/scss/_bootstrap-mincer.scss
xstatic/pkg/bootstrap_scss/data/scss/_bootstrap-sprockets.scss
xstatic/pkg/bootstrap_scss/data/scss/_bootstrap.scss
xstatic/pkg/bootstrap_scss/data/scss/bootstrap/_alerts.scss
xstatic/pkg/bootstrap_scss/data/scss/bootstrap/_badges.scss
xstatic/pkg/bootstrap_scss/data/scss/bootstrap/_breadcrumbs.scss
xstatic/pkg/bootstrap_scss/data/scss/bootstrap/_button-groups.scss
xstatic/pkg/bootstrap_scss/data/scss/bootstrap/_buttons.scss
xstatic/pkg/bootstrap_scss/data/scss/bootstrap/_carousel.scss
