Metadata-Version: 2.0
Name: XStatic-Bootstrap-SCSS
Version: 3.3.7.1
Summary: Bootstrap-SCSS 3.3.7 (XStatic packaging standard)
Home-page: http://getbootstrap.com/
Author: Radomir Dopieralski
Author-email: openstack@sheep.art.pl
License: MIT
Keywords: bootstrap_scss xstatic
Platform: any
